video2dataset/__init__.py
video2dataset/data_reader.py
video2dataset/data_writer.py
video2dataset/distributor.py
video2dataset/input_sharder.py
video2dataset/logger.py
video2dataset/main.py
video2dataset/output_sharder.py
video2dataset/slurm_executor.py
video2dataset/types.py
video2dataset/configs/__init__.py
video2dataset/configs/caption.yaml
video2dataset/configs/default.yaml
video2dataset/configs/downsample_ml.yaml
video2dataset/configs/optical_flow.yaml
video2dataset/dataloader/__init__.py
video2dataset/dataloader/audio_decode.py
video2dataset/dataloader/custom_wds.py
video2dataset/dataloader/dataloader.py
video2dataset/dataloader/filters.py
video2dataset/dataloader/transform.py
video2dataset/dataloader/video_decode.py
video2dataset/subsamplers/__init__.py
video2dataset/subsamplers/audio_rate_subsampler.py
video2dataset/subsamplers/caption_subsampler.py
video2dataset/subsamplers/clipping_subsampler.py
video2dataset/subsamplers/cut_detection_subsampler.py
video2dataset/subsamplers/ffprobe_subsampler.py
video2dataset/subsamplers/frame_subsampler.py
video2dataset/subsamplers/noop_subsampler.py
video2dataset/subsamplers/optical_flow_subsampler.py
video2dataset/subsamplers/resolution_subsampler.py
video2dataset/subsamplers/subsampler.py
video2dataset/subsamplers/whisper_subsampler.py
video2dataset/workers/__init__.py
video2dataset/workers/caption_worker.py
video2dataset/workers/download_worker.py
video2dataset/workers/optical_flow_worker.py
video2dataset/workers/subset_worker.py
video2dataset/workers/whisper_worker.py
video2dataset-1.3.0.data/data/README.md
video2dataset-1.3.0.data/data/caption.yaml
video2dataset-1.3.0.data/data/default.yaml
video2dataset-1.3.0.data/data/downsample_ml.yaml
video2dataset-1.3.0.data/data/optical_flow.yaml
video2dataset-1.3.0.dist-info/LICENSE
video2dataset-1.3.0.dist-info/METADATA
video2dataset-1.3.0.dist-info/WHEEL
video2dataset-1.3.0.dist-info/entry_points.txt
video2dataset-1.3.0.dist-info/top_level.txt
video2dataset-1.3.0.dist-info/RECORD
