Metadata-Version: 2.1
Name: video2dataset
Version: 1.3.0
Summary: Easily create large video dataset from video urls
Home-page: https://github.com/iejMac/video2dataset
Author: Maciej Kilian
Author-email: kilianmaciej6@gmail.com
License: MIT
Keywords: machine learning
Platform: UNKNOWN
Classifier: Development Status :: 4 - Beta
Classifier: Intended Audience :: Developers
Classifier: Topic :: Scientific/Engineering :: Artificial Intelligence
Classifier: License :: OSI Approved :: MIT License
Classifier: Programming Language :: Python :: 3.6
Requires-Dist: numpy <2,>=1.19.5
Requires-Dist: fire <0.6.0,>=0.4.0
Requires-Dist: requests <3,>=2.27.1
Requires-Dist: ffmpeg-python
Requires-Dist: yt-dlp
Requires-Dist: pyarrow
Requires-Dist: fsspec
Requires-Dist: webdataset
Requires-Dist: webvtt-py
Requires-Dist: wandb
Requires-Dist: pandas
Requires-Dist: tqdm
Requires-Dist: timeout-decorator
Requires-Dist: scenedetect[opencv] ==0.6.2
Requires-Dist: decord
Requires-Dist: torch ==2.1.2
Requires-Dist: langdetect
Requires-Dist: torchdata ==0.7.1
Requires-Dist: torchaudio ==2.1.2
Requires-Dist: soundfile
Requires-Dist: omegaconf
Requires-Dist: einops
Requires-Dist: transformers ==4.37.1
Requires-Dist: Pillow
Requires-Dist: accelerate
Requires-Dist: bitsandbytes
Requires-Dist: scipy
